MANIFEST.in
setup.cfg
setup.py
etc/pps_reader.cfg
pypps_reader/__init__.py
pypps_reader/version.py
pypps_reader.egg-info/PKG-INFO
pypps_reader.egg-info/SOURCES.txt
pypps_reader.egg-info/dependency_links.txt
pypps_reader.egg-info/not-zip-safe
pypps_reader.egg-info/requires.txt
pypps_reader.egg-info/top_level.txt
test/test_ppsread.py