Metadata-Version: 1.0
Name: pypps-reader
Version: v0.1.1
Summary: NWCSAF pps data reader
Home-page: https://github.com/adybbroe/pypps_reader
Author: Adam Dybbroe
Author-email: adam.dybbroe@smhi.se
License: GPLv3
Download-URL: https://github.com/adybbroe/pypps_reader/tarball/0.1.1 #egg=pypps_reader-v0.1.1
Platform: UNKNOWN
Classifier: Development Status :: 4 - Beta
Classifier: Intended Audience :: Science/Research
Classifier: License :: OSI Approved :: GNU General Public License v3 or later (GPLv3+)
Classifier: Operating System :: OS Independent
Classifier: Programming Language :: Python
Classifier: Topic :: Scientific/Engineering
